{
  "basic": {
    "1d": {
      "price": 1549.9266666666667
    },
    "3d": {
      "price": 1557.9133333333334
    },
    "7d": {
      "price": 1580.1133333333335
    },
    "14d": {
      "price": 1612.9533333333334
    },
    "30d": {
      "price": 2072.8866666666668
    },
    "timestamp": 1758230600.647275,
    "model": "basic_naive",
    "updated_at": "2025-09-19 00:23:20"
  },
  "_metadata": {
    "symbol": "CLEBI",
    "last_updated": 1758230600.647275,
    "update_count": 22
  },
  "enhanced": {
    "1d": {
      "ensemble_prediction": 1570.7462309986633,
      "confidence": 0.55,
      "models": {
        "xgboost": {
          "prediction": 1584.7328268196434,
          "confidence": 0.0,
          "rmse": 0.0,
          "mape": 0.0
        },
        "lightgbm": {
          "prediction": 1567.9683790854467,
          "confidence": 0.0,
          "rmse": 0.0,
          "mape": 0.0
        },
        "catboost": {
          "prediction": 1559.5374870909002,
          "confidence": 0.0,
          "rmse": 0.0,
          "mape": 0.0
        }
      },
      "current_price": 1547.0,
      "model_count": 3
    },
    "3d": {
      "ensemble_prediction": 1607.543389462632,
      "confidence": 0.55,
      "models": {
        "xgboost": {
          "prediction": 1641.8288901522756,
          "confidence": 0.0,
          "rmse": 0.0,
          "mape": 0.0
        },
        "lightgbm": {
          "prediction": 1589.5940272222365,
          "confidence": 0.0,
          "rmse": 0.0,
          "mape": 0.0
        },
        "catboost": {
          "prediction": 1591.2072510133835,
          "confidence": 0.0,
          "rmse": 0.0,
          "mape": 0.0
        }
      },
      "current_price": 1547.0,
      "model_count": 3
    },
    "7d": {
      "ensemble_prediction": 1639.9848411974344,
      "confidence": 0.55,
      "models": {
        "xgboost": {
          "prediction": 1613.7198208272457,
          "confidence": 0.0,
          "rmse": 0.0,
          "mape": 0.0
        },
        "lightgbm": {
          "prediction": 1652.6204445919855,
          "confidence": 0.0,
          "rmse": 0.0,
          "mape": 0.0
        },
        "catboost": {
          "prediction": 1653.6142581730717,
          "confidence": 0.0,
          "rmse": 0.0,
          "mape": 0.0
        }
      },
      "current_price": 1547.0,
      "model_count": 3
    },
    "14d": {
      "ensemble_prediction": 1642.9066354035767,
      "confidence": 0.55,
      "models": {
        "xgboost": {
          "prediction": 1624.3889822475612,
          "confidence": 0.0,
          "rmse": 0.0,
          "mape": 0.0
        },
        "lightgbm": {
          "prediction": 1639.9430187781309,
          "confidence": 0.0,
          "rmse": 0.0,
          "mape": 0.0
        },
        "catboost": {
          "prediction": 1664.387905185038,
          "confidence": 0.0,
          "rmse": 0.0,
          "mape": 0.0
        }
      },
      "current_price": 1547.0,
      "model_count": 3
    },
    "30d": {
      "ensemble_prediction": 1762.9946754785278,
      "confidence": 0.55,
      "models": {
        "xgboost": {
          "prediction": 1821.007752224803,
          "confidence": 0.0,
          "rmse": 0.0,
          "mape": 0.0
        },
        "lightgbm": {
          "prediction": 1778.546449204799,
          "confidence": 0.0,
          "rmse": 0.0,
          "mape": 0.0
        },
        "catboost": {
          "prediction": 1689.4298250059812,
          "confidence": 0.0,
          "rmse": 0.0,
          "mape": 0.0
        }
      },
      "current_price": 1547.0,
      "model_count": 3
    },
    "timestamp": 1758230600.647275,
    "updated_at": "2025-09-19 00:23:20"
  }
}