{
  "basic": {
    "1d": {
      "price": 3.3833
    },
    "3d": {
      "price": 3.3687333333333336
    },
    "7d": {
      "price": 3.2905333333333333
    },
    "14d": {
      "price": 2.9311333333333334
    },
    "30d": {
      "price": 2.1721333333333335
    },
    "timestamp": 1758145567.7056987,
    "model": "basic_naive",
    "updated_at": "2025-09-18 00:46:07"
  },
  "_metadata": {
    "symbol": "KATMR",
    "last_updated": 1758145567.7056987,
    "update_count": 8
  },
  "enhanced": {
    "1d": {
      "ensemble_prediction": 3.3084837082674254,
      "confidence": 0.55,
      "models": {
        "xgboost": {
          "prediction": 3.3120194927416744,
          "confidence": 0.0,
          "rmse": 0.0,
          "mape": 0.0
        },
        "lightgbm": {
          "prediction": 3.2787858045899583,
          "confidence": 0.0,
          "rmse": 0.0,
          "mape": 0.0
        },
        "catboost": {
          "prediction": 3.3346458274706436,
          "confidence": 0.0,
          "rmse": 0.0,
          "mape": 0.0
        }
      },
      "current_price": 3.39,
      "model_count": 3
    },
    "3d": {
      "ensemble_prediction": 3.2483430177562957,
      "confidence": 0.55,
      "models": {
        "xgboost": {
          "prediction": 3.134085169136524,
          "confidence": 0.0,
          "rmse": 0.0,
          "mape": 0.0
        },
        "lightgbm": {
          "prediction": 3.230009661675762,
          "confidence": 0.0,
          "rmse": 0.0,
          "mape": 0.0
        },
        "catboost": {
          "prediction": 3.380934222456601,
          "confidence": 0.0,
          "rmse": 0.0,
          "mape": 0.0
        }
      },
      "current_price": 3.39,
      "model_count": 3
    },
    "7d": {
      "ensemble_prediction": 2.996122928976554,
      "confidence": 0.55,
      "models": {
        "xgboost": {
          "prediction": 2.987513353228569,
          "confidence": 0.0,
          "rmse": 0.0,
          "mape": 0.0
        },
        "lightgbm": {
          "prediction": 2.8797577099372704,
          "confidence": 0.0,
          "rmse": 0.0,
          "mape": 0.0
        },
        "catboost": {
          "prediction": 3.1210977237638233,
          "confidence": 0.0,
          "rmse": 0.0,
          "mape": 0.0
        }
      },
      "current_price": 3.39,
      "model_count": 3
    },
    "14d": {
      "ensemble_prediction": 3.124850999376777,
      "confidence": 0.55,
      "models": {
        "xgboost": {
          "prediction": 3.166720874235034,
          "confidence": 0.0,
          "rmse": 0.0,
          "mape": 0.0
        },
        "lightgbm": {
          "prediction": 3.1459290074677217,
          "confidence": 0.0,
          "rmse": 0.0,
          "mape": 0.0
        },
        "catboost": {
          "prediction": 3.061903116427574,
          "confidence": 0.0,
          "rmse": 0.0,
          "mape": 0.0
        }
      },
      "current_price": 3.39,
      "model_count": 3
    },
    "30d": {
      "ensemble_prediction": 2.5864771794117796,
      "confidence": 0.55,
      "models": {
        "xgboost": {
          "prediction": 2.626177032440901,
          "confidence": 0.0,
          "rmse": 0.0,
          "mape": 0.0
        },
        "lightgbm": {
          "prediction": 2.5208196900406104,
          "confidence": 0.0,
          "rmse": 0.0,
          "mape": 0.0
        },
        "catboost": {
          "prediction": 2.6124348157538275,
          "confidence": 0.0,
          "rmse": 0.0,
          "mape": 0.0
        }
      },
      "current_price": 3.39,
      "model_count": 3
    },
    "timestamp": 1758145567.7056987,
    "updated_at": "2025-09-18 00:46:07"
  }
}