{
  "basic": {
    "1d": {
      "price": 195.8093333333333
    },
    "3d": {
      "price": 195.58933333333331
    },
    "7d": {
      "price": 194.10066666666665
    },
    "14d": {
      "price": 192.30533333333332
    },
    "30d": {
      "price": 191.76866666666666
    },
    "timestamp": 1758145874.2486641,
    "model": "basic_naive",
    "updated_at": "2025-09-18 00:51:14"
  },
  "_metadata": {
    "symbol": "SDTTR",
    "last_updated": 1758145874.2486641,
    "update_count": 6
  },
  "enhanced": {
    "1d": {
      "ensemble_prediction": 197.0523133912137,
      "confidence": 0.55,
      "models": {
        "xgboost": {
          "prediction": 197.97957852715626,
          "confidence": 0.0,
          "rmse": 0.0,
          "mape": 0.0
        },
        "lightgbm": {
          "prediction": 195.7902323072753,
          "confidence": 0.0,
          "rmse": 0.0,
          "mape": 0.0
        },
        "catboost": {
          "prediction": 197.38712933920942,
          "confidence": 0.0,
          "rmse": 0.0,
          "mape": 0.0
        }
      },
      "current_price": 195.7,
      "model_count": 3
    },
    "3d": {
      "ensemble_prediction": 196.3514906889956,
      "confidence": 0.55,
      "models": {
        "xgboost": {
          "prediction": 197.73544476842505,
          "confidence": 0.0,
          "rmse": 0.0,
          "mape": 0.0
        },
        "lightgbm": {
          "prediction": 194.98393355941448,
          "confidence": 0.0,
          "rmse": 0.0,
          "mape": 0.0
        },
        "catboost": {
          "prediction": 196.33509373914725,
          "confidence": 0.0,
          "rmse": 0.0,
          "mape": 0.0
        }
      },
      "current_price": 195.7,
      "model_count": 3
    },
    "7d": {
      "ensemble_prediction": 195.1275943041991,
      "confidence": 0.55,
      "models": {
        "xgboost": {
          "prediction": 193.6680992739275,
          "confidence": 0.0,
          "rmse": 0.0,
          "mape": 0.0
        },
        "lightgbm": {
          "prediction": 196.40834520936463,
          "confidence": 0.0,
          "rmse": 0.0,
          "mape": 0.0
        },
        "catboost": {
          "prediction": 195.3063384293052,
          "confidence": 0.0,
          "rmse": 0.0,
          "mape": 0.0
        }
      },
      "current_price": 195.7,
      "model_count": 3
    },
    "14d": {
      "ensemble_prediction": 194.34048761035936,
      "confidence": 0.55,
      "models": {
        "xgboost": {
          "prediction": 190.5302670545876,
          "confidence": 0.0,
          "rmse": 0.0,
          "mape": 0.0
        },
        "lightgbm": {
          "prediction": 195.7235950722977,
          "confidence": 0.0,
          "rmse": 0.0,
          "mape": 0.0
        },
        "catboost": {
          "prediction": 196.76760070419277,
          "confidence": 0.0,
          "rmse": 0.0,
          "mape": 0.0
        }
      },
      "current_price": 195.7,
      "model_count": 3
    },
    "30d": {
      "ensemble_prediction": 187.85634514885032,
      "confidence": 0.55,
      "models": {
        "xgboost": {
          "prediction": 186.52694524563847,
          "confidence": 0.0,
          "rmse": 0.0,
          "mape": 0.0
        },
        "lightgbm": {
          "prediction": 188.0033218074047,
          "confidence": 0.0,
          "rmse": 0.0,
          "mape": 0.0
        },
        "catboost": {
          "prediction": 189.03876839350772,
          "confidence": 0.0,
          "rmse": 0.0,
          "mape": 0.0
        }
      },
      "current_price": 195.7,
      "model_count": 3
    },
    "timestamp": 1758145874.2486641,
    "updated_at": "2025-09-18 00:51:14"
  }
}