{
  "best_value": 79.46428571428572,
  "best_dirhit": 79.46428571428572,
  "best_params": {
    "enable_external_features": true,
    "enable_fingpt_features": true,
    "enable_yolo_features": false,
    "enable_directional_loss": false,
    "enable_seed_bagging": true,
    "enable_talib_patterns": true,
    "enable_smart_ensemble": false,
    "enable_stacked_short": true,
    "enable_meta_stacking": false,
    "enable_regime_detection": false,
    "enable_fingpt": true,
    "model_choice": "xgb",
    "n_seeds": 2,
    "ml_adaptive_k_1d": 2.5720788565201635,
    "ml_pattern_weight_scale_1d": 1.1041493647534526,
    "enable_talib_patterns_short": true,
    "external_min_days": 24,
    "external_smooth_alpha": 0.2455591205910015,
    "fingpt_confidence_threshold": 0.35491402262456034,
    "xgb_n_estimators": 273,
    "xgb_max_depth": 2,
    "xgb_learning_rate": 0.07208540508000964,
    "xgb_subsample": 0.5890089184392205,
    "xgb_colsample_bytree": 0.5734893104301367,
    "xgb_reg_alpha": 8.860339922601941e-06,
    "xgb_reg_lambda": 0.0019442083167198567,
    "xgb_min_child_weight": 8,
    "xgb_gamma": 0.001194457688608885,
    "xgb_grow_policy": "depthwise",
    "xgb_tree_method": "hist",
    "xgb_max_bin": 354
  },
  "best_trial": {
    "number": 809,
    "value": 49.381478920697546,
    "state": "1"
  },
  "best_trial_number": 809,
  "best_trial_seed": 851,
  "n_trials": 1420,
  "pruned_count": 0,
  "avg_trial_time": 0.0,
  "top_k_trials": [],
  "study_name": "hpo_with_features_BIOEN_h1_c2",
  "symbols": [
    "BIOEN"
  ],
  "horizon": 1,
  "best_model_choice": "xgb",
  "feature_flags": {
    "enable_external_features": true,
    "enable_fingpt_features": true,
    "enable_yolo_features": false,
    "enable_directional_loss": false,
    "enable_seed_bagging": true,
    "enable_talib_patterns": true,
    "enable_smart_ensemble": false,
    "enable_stacked_short": true,
    "enable_meta_stacking": false,
    "enable_regime_detection": false,
    "enable_fingpt": true,
    "enable_talib_patterns_short": true
  },
  "feature_params": {
    "n_seeds": 2,
    "ml_adaptive_k_1d": 2.5720788565201635,
    "ml_pattern_weight_scale_1d": 1.1041493647534526,
    "external_min_days": 24,
    "external_smooth_alpha": 0.2455591205910015,
    "fingpt_confidence_threshold": 0.35491402262456034
  },
  "hyperparameters": {
    "model_choice": "xgb",
    "xgb_n_estimators": 273,
    "xgb_max_depth": 2,
    "xgb_learning_rate": 0.07208540508000964,
    "xgb_subsample": 0.5890089184392205,
    "xgb_colsample_bytree": 0.5734893104301367,
    "xgb_reg_alpha": 8.860339922601941e-06,
    "xgb_reg_lambda": 0.0019442083167198567,
    "xgb_min_child_weight": 8,
    "xgb_gamma": 0.001194457688608885,
    "xgb_grow_policy": "depthwise",
    "xgb_tree_method": "hist",
    "xgb_max_bin": 354
  },
  "features_enabled": {
    "ENABLE_EXTERNAL_FEATURES": "1",
    "ENABLE_FINGPT_FEATURES": "1",
    "ENABLE_YOLO_FEATURES": "0",
    "ML_USE_DIRECTIONAL_LOSS": "0",
    "ENABLE_SEED_BAGGING": "1",
    "ENABLE_TALIB_PATTERNS": "1",
    "ML_USE_SMART_ENSEMBLE": "0",
    "ML_USE_STACKED_SHORT": "1",
    "ENABLE_META_STACKING": "0",
    "ML_USE_REGIME_DETECTION": "0",
    "ENABLE_FINGPT": "1",
    "ML_USE_ADAPTIVE_LEARNING": "0",
    "ENABLE_XGBOOST": "1",
    "ENABLE_LIGHTGBM": "0",
    "ENABLE_CATBOOST": "0"
  },
  "best_trial_metrics": {
    "BIOEN_1d": {
      "symbol": "BIOEN",
      "horizon": 1,
      "split_metrics": [
        {
          "split_index": 1,
          "train_days": 453,
          "test_days": 30,
          "train_end_idx": 453,
          "test_end_idx": 483,
          "train_start": "2023-08-21T00:00:00",
          "train_end": "2025-06-12T00:00:00",
          "test_start": "2025-06-13T00:00:00",
          "test_end": "2025-07-25T00:00:00",
          "valid_predictions": 29,
          "model_metrics": {
            "xgboost": {
              "raw_r2": 0.0035199515631413325,
              "rmse": 0.02851429920029537,
              "mape": 1.8127483092029866,
              "confidence": 0.6278598868242532
            }
          },
          "dirhit": 87.5,
          "rmse": 0.015624448512218704,
          "mape": 175.75372793552003,
          "nrmse": 0.9389360349401145,
          "mask_count": 16,
          "mask_pct": 55.172413793103445,
          "low_support": false,
          "min_mask_count": 10,
          "min_mask_pct": 5.0
        },
        {
          "split_index": 2,
          "train_days": 483,
          "test_days": 30,
          "train_end_idx": 483,
          "test_end_idx": 513,
          "train_start": "2023-08-21T00:00:00",
          "train_end": "2025-07-25T00:00:00",
          "test_start": "2025-07-28T00:00:00",
          "test_end": "2025-09-05T00:00:00",
          "valid_predictions": 29,
          "model_metrics": {
            "xgboost": {
              "raw_r2": 0.02918069453636411,
              "rmse": 0.027595860323974482,
              "mape": 1.600713858429638,
              "confidence": 0.648667343680321
            }
          },
          "dirhit": null,
          "rmse": 0.03208661810628253,
          "mape": 1805338.039857605,
          "nrmse": 0.9377546449540238,
          "mask_count": 9,
          "mask_pct": 31.03448275862069,
          "low_support": true,
          "min_mask_count": 10,
          "min_mask_pct": 5.0
        },
        {
          "split_index": 3,
          "train_days": 513,
          "test_days": 30,
          "train_end_idx": 513,
          "test_end_idx": 543,
          "train_start": "2023-08-21T00:00:00",
          "train_end": "2025-09-05T00:00:00",
          "test_start": "2025-09-08T00:00:00",
          "test_end": "2025-10-17T00:00:00",
          "valid_predictions": 29,
          "model_metrics": {
            "xgboost": {
              "raw_r2": 0.04519672332306157,
              "rmse": 0.027370379679192362,
              "mape": 1.6106969910857376,
              "confidence": 0.6615668518469235
            }
          },
          "dirhit": 71.42857142857143,
          "rmse": 0.027794855044451994,
          "mape": 125.49648824587348,
          "nrmse": 1.0785972572901223,
          "mask_count": 14,
          "mask_pct": 48.275862068965516,
          "low_support": false,
          "min_mask_count": 10,
          "min_mask_pct": 5.0
        },
        {
          "split_index": 4,
          "train_days": 543,
          "test_days": 30,
          "train_end_idx": 543,
          "test_end_idx": 573,
          "train_start": "2023-08-21T00:00:00",
          "train_end": "2025-10-17T00:00:00",
          "test_start": "2025-10-20T00:00:00",
          "test_end": "2025-11-28T00:00:00",
          "valid_predictions": 29,
          "model_metrics": {
            "xgboost": {
              "raw_r2": 0.046361782639526505,
              "rmse": 0.02743928836250542,
              "mape": 1.6057198703202742,
              "confidence": 0.662501170318398
            }
          },
          "dirhit": null,
          "rmse": 0.02161250464231756,
          "mape": 5136250.428638104,
          "nrmse": 1.2070594490173743,
          "mask_count": 3,
          "mask_pct": 10.344827586206897,
          "low_support": true,
          "min_mask_count": 10,
          "min_mask_pct": 5.0
        }
      ],
      "avg_dirhit": 79.46428571428572,
      "avg_nrmse": 1.0405868465504087,
      "split_count": 4,
      "avg_model_metrics": {
        "xgboost": {
          "raw_r2": 0.03106478801552338,
          "rmse": 0.027729956891491908,
          "mape": 1.657469757259659,
          "confidence": 0.650148813167474
        }
      }
    }
  },
  "evaluation_spec": {
    "horizon": 1,
    "dirhit_threshold": 0.005,
    "min_mask_count": 5,
    "min_mask_pct": 2.5,
    "best_trial_number": 809,
    "best_trial_seed": 851,
    "scoring": {
      "formula": "score = 0.7*avg_dirhit - k*avg_nrmse",
      "k": 6.0
    },
    "symbol_specs": {
      "BIOEN_1d": {
        "splits": [
          {
            "split_index": 1,
            "train_end_idx": 453,
            "test_end_idx": 483,
            "train_start": "2023-08-21T00:00:00",
            "train_end": "2025-06-12T00:00:00",
            "test_start": "2025-06-13T00:00:00",
            "test_end": "2025-07-25T00:00:00"
          },
          {
            "split_index": 2,
            "train_end_idx": 483,
            "test_end_idx": 513,
            "train_start": "2023-08-21T00:00:00",
            "train_end": "2025-07-25T00:00:00",
            "test_start": "2025-07-28T00:00:00",
            "test_end": "2025-09-05T00:00:00"
          },
          {
            "split_index": 3,
            "train_end_idx": 513,
            "test_end_idx": 543,
            "train_start": "2023-08-21T00:00:00",
            "train_end": "2025-09-05T00:00:00",
            "test_start": "2025-09-08T00:00:00",
            "test_end": "2025-10-17T00:00:00"
          },
          {
            "split_index": 4,
            "train_end_idx": 543,
            "test_end_idx": 573,
            "train_start": "2023-08-21T00:00:00",
            "train_end": "2025-10-17T00:00:00",
            "test_start": "2025-10-20T00:00:00",
            "test_end": "2025-11-28T00:00:00"
          }
        ]
      }
    }
  },
  "_created_at": "2025-12-03T03:33:08.130419",
  "_created_from": "study_database",
  "_filter_applied": {
    "min_mask_count": 5,
    "min_mask_pct": 2.5
  }
}